{
  "openapi": "3.1.0",
  "info": {
    "title": "管理员禁用用户2FA",
    "version": "1.0.0",
    "description": "👨‍💼 需要管理员权限（Admin）"
  },
  "servers": [
    {
      "url": "https://api.txtoken.cn"
    }
  ],
  "tags": [
    {
      "name": "用户管理"
    }
  ],
  "paths": {
    "/api/user/{id}/2fa": {
      "delete": {
        "tags": [
          "用户管理"
        ],
        "summary": "管理员禁用用户2FA",
        "description": "👨‍💼 需要管理员权限（Admin）",
        "operationId": "delete-api-user-id-2fa",
        "parameters": [
          {
            "name": "id",
            "in": "path",
            "required": true,
            "schema": {
              "type": "integer"
            }
          }
        ],
        "responses": {
          "200": {
            "description": "成功"
          }
        }
      }
    }
  }
}
